awspytools/DynamoDBDataStore.py
awspytools/__init__.py
awspytools-0.1.1.dist-info/LICENSE
awspytools-0.1.1.dist-info/METADATA
awspytools-0.1.1.dist-info/WHEEL
awspytools-0.1.1.dist-info/top_level.txt
awspytools-0.1.1.dist-info/RECORD
