Metadata-Version: 2.1
Name: awspytools
Version: 0.1.1
Summary: A collection of tools to try and make AWS boto3 more pythonic
Home-page: https://github.com/a2d24/awspytools
Author: Yusuff Lockhat
Author-email: awspytools@a2d24.com
License: UNKNOWN
Platform: UNKNOWN
Classifier: Programming Language :: Python :: 3
Classifier: Programming Language :: Python :: 3.5
Classifier: Programming Language :: Python :: 3.6
Classifier: Programming Language :: Python :: 3.7
Classifier: Programming Language :: Python :: 3.8
Classifier: Programming Language :: Python :: 3 :: Only
Classifier: License :: OSI Approved :: MIT License
Classifier: Operating System :: OS Independent
Requires-Python: >=3.0
Requires-Dist: boto3
